CHANGES.txt
MANIFEST.in
README.txt
setup.py
docs/HISTORY.txt
docs/LICENSE.GPL
docs/LICENSE.txt
src/mediacore/__init__.py
src/mediacore.mediainfo.egg-info/PKG-INFO
src/mediacore.mediainfo.egg-info/SOURCES.txt
src/mediacore.mediainfo.egg-info/dependency_links.txt
src/mediacore.mediainfo.egg-info/entry_points.txt
src/mediacore.mediainfo.egg-info/namespace_packages.txt
src/mediacore.mediainfo.egg-info/not-zip-safe
src/mediacore.mediainfo.egg-info/requires.txt
src/mediacore.mediainfo.egg-info/top_level.txt
src/mediacore/mediainfo/__init__.py
src/mediacore/mediainfo/controller.py
src/mediacore/mediainfo/media_metadata.py