Metadata-Version: 1.1
Name: mediacore.mediainfo
Version: 0.9.3
Summary: Mediacore.mediainfo provides info about media file as JSON
Home-page: UNKNOWN
Author: RedTurtle
Author-email: sviluppoplone@redturtle.it
License: gpl
Keywords: Mediacore
Platform: UNKNOWN
Classifier: Programming Language :: Python
